flask/__init__.py
flask/__main__.py
flask/app.py
flask/blueprints.py
flask/cli.py
flask/config.py
flask/ctx.py
flask/debughelpers.py
flask/globals.py
flask/helpers.py
flask/logging.py
flask/py.typed
flask/scaffold.py
flask/sessions.py
flask/signals.py
flask/templating.py
flask/testing.py
flask/typing.py
flask/views.py
flask/wrappers.py
flask/json/__init__.py
flask/json/provider.py
flask/json/tag.py
flask_mirror_upstream-2.3.4.dist-info/entry_points.txt
flask_mirror_upstream-2.3.4.dist-info/LICENSE.rst
flask_mirror_upstream-2.3.4.dist-info/WHEEL
flask_mirror_upstream-2.3.4.dist-info/METADATA
flask_mirror_upstream-2.3.4.dist-info/RECORD
