Metadata-Version: 2.1
Name: Flask-Mirror-Upstream
Version: 2.3.4
Summary: A simple framework for building complex web applications.
Maintainer-email: Pallets <contact@palletsprojects.com>
Requires-Python: >=3.8
Classifier: Development Status :: 5 - Production/Stable
Classifier: Environment :: Web Environment
Classifier: Framework :: Flask
Classifier: Intended Audience :: Developers
Classifier: License :: OSI Approved :: BSD License
Classifier: Operating System :: OS Independent
Classifier: Programming Language :: Python
Classifier: Topic :: Internet :: WWW/HTTP :: Dynamic Content
Classifier: Topic :: Internet :: WWW/HTTP :: WSGI
Classifier: Topic :: Internet :: WWW/HTTP :: WSGI :: Application
Classifier: Topic :: Software Development :: Libraries :: Application Frameworks
Requires-Dist: Werkzeug>=2.3.7
Requires-Dist: Jinja2>=3.1.2
Requires-Dist: itsdangerous>=2.1.2
Requires-Dist: click>=8.1.3
Requires-Dist: blinker>=1.6.2
Requires-Dist: importlib-metadata>=3.6.0; python_version < '3.10'
Requires-Dist: asgiref>=3.2 ; extra == "async"
Requires-Dist: python-dotenv ; extra == "dotenv"
Project-URL: Changes, https://flask.palletsprojects.com/changes/
Project-URL: Chat, https://discord.gg/pallets
Project-URL: Documentation, https://flask.palletsprojects.com/
Project-URL: Donate, https://palletsprojects.com/donate
Project-URL: Issue Tracker, https://github.com/pallets/flask/issues/
Project-URL: Source Code, https://github.com/pallets/flask/
Provides-Extra: async
Provides-Extra: dotenv
